Metadata-Version: 2.1
Name: datalogue-dev
Version: 2022.3.15.1647358971
Summary: SDK to interact with the datalogue platform
Home-page: https://github.com/datalogue/platform
Author: Nicolas Joseph
Author-email: nic@datalogue.io
License: 
Platform: UNKNOWN
Classifier: Programming Language :: Python :: 3
Classifier: Programming Language :: Python :: 3.6
Classifier: Programming Language :: Python :: 3.7
Classifier: Programming Language :: Python :: 3.8
Classifier: Programming Language :: Python :: 3.9
Classifier: Operating System :: OS Independent
Requires-Python: >=3.6
